fastack_cache/__init__.py
fastack_cache/backends/__init__.py
fastack_cache/backends/aioredis.py
fastack_cache/backends/base.py
fastack_cache/backends/dummy.py
fastack_cache/backends/redis.py
fastack_cache/decorators.py
fastack_cache/globals.py
fastack_cache/helpers.py
fastack_cache/key.py
fastack_cache/serializers/__init__.py
fastack_cache/serializers/base.py
fastack_cache/serializers/json.py
fastack_cache/serializers/pickle.py
fastack_cache-1.2.0.dist-info/LICENSE
fastack_cache-1.2.0.dist-info/WHEEL
fastack_cache-1.2.0.dist-info/METADATA
fastack_cache-1.2.0.dist-info/RECORD
