Metadata-Version: 2.1
Name: fastack-cache
Version: 1.2.0
Summary: Caching plugin for fastack
Home-page: https://github.com/fastack-dev/fastack-cache
License: MIT
Author: aprilahijriyan
Author-email: 37798612+aprilahijriyan@users.noreply.github.com
Maintainer: aprilahijriyan
Maintainer-email: 37798612+aprilahijriyan@users.noreply.github.com
Requires-Python: >=3.7,<3.10
Classifier: Development Status :: 4 - Beta
Classifier: Environment :: Web Environment
Classifier: Intended Audience :: Developers
Classifier: Intended Audience :: Information Technology
Classifier: Intended Audience :: System Administrators
Classifier: License :: OSI Approved :: MIT License
Classifier: Operating System :: OS Independent
Classifier: Programming Language :: Python
Classifier: Programming Language :: Python :: 3
Classifier: Programming Language :: Python :: 3 :: Only
Classifier: Programming Language :: Python :: 3.7
Classifier: Programming Language :: Python :: 3.8
Classifier: Programming Language :: Python :: 3.9
Classifier: Topic :: Internet
Classifier: Topic :: Software Development
Classifier: Topic :: Software Development :: Libraries
Classifier: Topic :: Software Development :: Libraries :: Python Modules
Provides-Extra: aioredis
Provides-Extra: redis
Requires-Dist: aioredis (>=2.0.1,<3.0.0); extra == "aioredis"
Requires-Dist: fastack (>=4.0.0,<5.0.0)
Requires-Dist: redis (>=4.1.1,<5.0.0); extra == "redis"
Project-URL: Bug Tracker, https://github.com/fastack-dev/fastack-cache/issues
Project-URL: Repository, https://github.com/fastack-dev/fastack-cache
